otlp_exporter/__init__.py
otlp_exporter/handler.py
django_otlp_log_exporter-1.0.3.dist-info/METADATA
django_otlp_log_exporter-1.0.3.dist-info/WHEEL
django_otlp_log_exporter-1.0.3.dist-info/top_level.txt
django_otlp_log_exporter-1.0.3.dist-info/RECORD
