Metadata-Version: 2.1
Name: django-otlp-log-exporter
Version: 1.0.3
Summary: integrate Django & SDK provided by OpenTelemetry and directly forward the logs from the application to OpenTelemetry.
Home-page: https://github.com/mojtabaakbari221b/django_otlp_log_exporter
Author: Mojtaba Akbari
Author-email: mojtaba.akbari.221b@gmail.com
License: MIT
Requires-Python: >=3.7
Requires-Dist: opentelemetry-sdk (>=1.16.0)
Requires-Dist: opentelemetry-api (>=1.16.0)
Requires-Dist: opentelemetry-exporter-otlp (>=1.16.0)
Requires-Dist: Django (>=3.2)
